PGMInt/PGMI.py
PGMInt/Processors/AbstractProcessor.py
PGMInt/Processors/GaussianPacketProcessor.py
PGMInt/Processors/PixelProcessor.py
PGMInt/Processors/SlitProcessor.py
PGMInt/Processors/SourceGratingProcessor.py
PGMInt/Samples/AbstractSample.py
PGMInt/Samples/RectangleGrating.py
PGMInt/Samples/Slit.py
pgmint-1.1.dist-info/licenses/COPYING
pgmint-1.1.dist-info/METADATA
pgmint-1.1.dist-info/WHEEL
pgmint-1.1.dist-info/top_level.txt
pgmint-1.1.dist-info/RECORD
