Metadata-Version: 2.4
Name: PGMInt
Version: 1.1
Summary: See Readme
Author-email: "Davis V. Garrad" <dvlast@uwaterloo.ca>
License-Expression: GPL-3.0-only
Project-URL: Homepage, https://github.com/Davis-Garrad/Phase-Grating-Moire-Interferometry
Project-URL: Issues, https://github.com/Davis-Garrad/Phase-Grating-Moire-Interferometry/issues
Classifier: Programming Language :: Python :: 3
Classifier: Operating System :: OS Independent
Requires-Python: >=3.9
License-File: COPYING
Requires-Dist: numpy
Requires-Dist: matplotlib
Requires-Dist: dools
Dynamic: license-file
